tqrar/__init__.py
tqrar/_version.py
tqrar/handlers.py
tqrar/labextension/build_log.json
tqrar/labextension/package.json
tqrar/labextension/schemas/tqrar/package.json.orig
tqrar/labextension/schemas/tqrar/plugin.json
tqrar/labextension/static/373c04fd2418f5c77eea.eot
tqrar/labextension/static/3f6d3488cf65374f6f67.woff
tqrar/labextension/static/79d088064beb3826054f.eot
tqrar/labextension/static/8ea8791754915a898a31.woff2
tqrar/labextension/static/9674eb1bd55047179038.svg
tqrar/labextension/static/9834b82ad26e2a37583d.woff2
tqrar/labextension/static/Tqrar.png
tqrar/labextension/static/a3b9817780214caf01e8.svg
tqrar/labextension/static/af6397503fcefbd61397.ttf
tqrar/labextension/static/be0a084962d8066884f7.svg
tqrar/labextension/static/cb9e9e693192413cde2b.woff
tqrar/labextension/static/cda59d6efffa685830fd.ttf
tqrar/labextension/static/e4299464e7b012968eed.eot
tqrar/labextension/static/e42a88444448ac3d6054.woff2
tqrar/labextension/static/e8711bbb871afd8e9dea.ttf
tqrar/labextension/static/f9217f66874b0c01cd8c.woff
tqrar/labextension/static/ghost-logo.png
tqrar/labextension/static/lib_index_js.03c642d0c966e6300f09.js
tqrar/labextension/static/lib_index_js.03c642d0c966e6300f09.js.map
tqrar/labextension/static/lib_index_js.08504610f7be1e818bf3.js
tqrar/labextension/static/lib_index_js.08504610f7be1e818bf3.js.map
tqrar/labextension/static/lib_index_js.1c4fc9eb5c2616b7fce0.js
tqrar/labextension/static/lib_index_js.1c4fc9eb5c2616b7fce0.js.map
tqrar/labextension/static/lib_index_js.3b24e5bac032cda69a16.js
tqrar/labextension/static/lib_index_js.3b24e5bac032cda69a16.js.map
tqrar/labextension/static/lib_index_js.61a0ff7533cc70e189d4.js
tqrar/labextension/static/lib_index_js.61a0ff7533cc70e189d4.js.map
tqrar/labextension/static/lib_index_js.61f15e589f601bc0d4f5.js
tqrar/labextension/static/lib_index_js.61f15e589f601bc0d4f5.js.map
tqrar/labextension/static/lib_index_js.661754ffbcca2f89812f.js
tqrar/labextension/static/lib_index_js.661754ffbcca2f89812f.js.map
tqrar-0.3.0.dist-info/METADATA
tqrar-0.3.0.dist-info/WHEEL
tqrar-0.3.0.dist-info/licenses/LICENSE
tqrar-0.3.0.dist-info/RECORD
